{"assets/images/apple.png":["assets/images/apple.png"],"assets/images/banana.png":["assets/images/banana.png"],"assets/images/cherry.png":["assets/images/cherry.png"],"assets/images/grape.png":["assets/images/grape.png"],"assets/images/lemon.png":["assets/images/lemon.png"],"assets/images/orange.png":["assets/images/orange.png"],"assets/sounds/gameover.mp3":["assets/sounds/gameover.mp3"],"assets/sounds/match.mp3":["assets/sounds/match.mp3"],"assets/sounds/wrong.mp3":["assets/sounds/wrong.mp3"],"packages/cupertino_icons/assets/CupertinoIcons.ttf":["packages/cupertino_icons/assets/CupertinoIcons.ttf"]}